{
    "//": "ckiplab/albert-tiny-chinese",
    "model_name_or_path": "ckiplab/albert-base-chinese" ,
    "tokenizer_name" : "bert-base-chinese",
    "train_file": "./train_data/train_file_0323.json",
    "validation_file" : "./train_data/validation_file_0323.json",
    "test_file": "./train_data/test_file_0323.json",
    "label_file": "./label.json",
    "task_name" : "ner",
    "do_train" : true,
    "do_eval" : true,
    "do_predict" : true,
    "metric_for_best_model": "eval_f1",
    "load_best_model_at_end" : true,
    "overwrite_output_dir" :true,
    "output_dir": "./model/best_model_0329_1",
    "learning_rate": 5e-4,
    "eval_steps": 1000,
    "save_steps": 1000,
    "logging_steps": 1000,
    "evaluation_strategy": "steps",
    "num_train_epochs": 3.0,
    "per_device_train_batch_size": 8,
    "per_device_eval_batch_size": 8,
    "save_total_limit": 10,
    "warmup_ratio": 0.1,
    "preprocessing_num_workers":2,
    "logging_first_step": true,
    "ignore_data_skip": true,
    "return_entity_level_metrics": true

}